{
  "annotations": [
    {
      "start_time": 0,
      "end_time": 22,
      "annotation": [
        {
          "type": "paragraph",
          "children": [
            {
              "text": "Come the following – after I graduated, in September- at that time school started in September- I joined the Young Democrats with Rosie Castro. And I met Margret Castio and a lot of other people who remember me and I don't remember them."
            }
          ]
        }
      ],
      "tags": [
        {
          "tag": "Classmates",
          "category": "People"
        },
        {
          "tag": "The Young Democrats",
          "category": "Political Organizations"
        },
        {
          "tag": "Rosie Castro",
          "category": "People"
        }
      ],
      "uuid": "09a1e3e0-c777-4aa4-85e5-7536c0cf6cf9"
    },
    {
      "start_time": 22,
      "end_time": 39,
      "annotation": [
        {
          "type": "paragraph",
          "children": [
            {
              "text": "Before we get there, did you ever discuss the books, you know like the autobiography, with the Sisters? \"Oh, oh, Sister Margaret, Yes.\" And what sort of things did you talk about?"
            }
          ]
        }
      ],
      "tags": [
        {
          "tag": "Question About School Staff",
          "category": "Interviewer Question"
        }
      ],
      "uuid": "c2557cb0-eba1-4ff8-b0b9-40e437ae0d1c"
    },
    {
      "start_time": 39,
      "end_time": 95,
      "annotation": [
        {
          "type": "paragraph",
          "children": [
            {
              "text": "I told her that I thought it was surprising that a Catholic nun would give me a book about the Nation of Islam. I actually went looking for the Nation of Islam here in San Antonio. Because at that time, and I was young, I was stupid. You know, I didn't know. And I found them. They had their own little snack place or whatever they had- they use to make the zucchini bread and the carrot bread, all these nice breads. Because I wanted to join, I wanted to join the Nation of Islam because I wanted to know all about them. And I told her, and you know. She said go for it. \"Go fo it.\" I think she knew that they were not going to let me in because I was't black, you know. But, I still went and I found them."
            }
          ]
        }
      ],
      "tags": [
        {
          "tag": "School Staff",
          "category": "People"
        },
        {
          "tag": "The Nation of Islam",
          "category": "Political Organizations"
        }
      ],
      "uuid": "98ae0e76-ff53-4bc1-b6a7-2d7a09970348"
    },
    {
      "start_time": 95,
      "end_time": 97,
      "annotation": [
        {
          "type": "paragraph",
          "children": [
            {
              "text": "Where were they located?"
            }
          ]
        }
      ],
      "tags": [
        {
          "tag": "Question About Activism",
          "category": "Interviewer Question"
        }
      ],
      "uuid": "4946ce8d-ec35-46bd-b01b-0c49914d4b80"
    },
    {
      "start_time": 97,
      "end_time": 145,
      "annotation": [
        {
          "type": "paragraph",
          "children": [
            {
              "text": "They were on the Eastside on Houston. But you know, I could just take the bus straight down, just the bus the straight down. And uh, I forget- if they're still there I don't know. I don’t think they are. I do know because I taught in the west side- in the east side for a number of years. An there's a gentleman that still sells their little newsletter called \"The World\" or something like that. I use to give them quarters for the newspaper. You know and uh. It was, that was even now. I think the most recent was last year. So that was incredible, huh?"
            }
          ]
        }
      ],
      "tags": [
        {
          "tag": "The Nation of Islam",
          "category": "Political Organizations"
        },
        {
          "tag": "Literature",
          "category": "Reading and Writing"
        },
        {
          "category": "Places of San Antonio",
          "tag": "Streets of San Antonio"
        }
      ],
      "uuid": "1040ac1b-3981-4154-baaa-5c47f098eb64"
    },
    {
      "start_time": 145,
      "end_time": 151,
      "annotation": [
        {
          "type": "paragraph",
          "children": [
            {
              "text": "Can you tell me about- did you say you marched with the Lanier students? "
            }
          ]
        }
      ],
      "tags": [
        {
          "tag": "Question About Activism",
          "category": "Interviewer Question"
        }
      ],
      "uuid": "ea09231c-fcb9-47e5-9141-ae7303a02531"
    },
    {
      "start_time": 151,
      "end_time": 182,
      "annotation": [
        {
          "type": "paragraph",
          "children": [
            {
              "text": "I didn't march with them. I helped with the, I knew they were organizing and I helped to support. You know, some of them ended up at the Guadalupe Community Center. They didn't go to school. So they were there and I interacted with them. Edgar Lozano is one of them. Gosh! Speedy was the other one. Um, gosh, I'm trying to remember their names, Rodger..."
            }
          ]
        }
      ],
      "tags": [
        {
          "tag": "Classmates",
          "category": "People"
        },
        {
          "tag": "Education Activism",
          "category": "Activism"
        },
        {
          "tag": "School Walkouts",
          "category": "Activism"
        }
      ],
      "uuid": "56151e5f-ddcd-4338-ae84-e495f4f1d1a0"
    },
    {
      "start_time": 182,
      "end_time": 186,
      "annotation": [
        {
          "type": "paragraph",
          "children": [
            {
              "text": "Do you remember what their demands were? "
            }
          ]
        }
      ],
      "tags": [
        {
          "tag": "Question About Activism",
          "category": "Interviewer Question"
        }
      ],
      "uuid": "3b8040d7-50db-497b-8d87-5419ad5ba8a6"
    },
    {
      "start_time": 186,
      "end_time": 211,
      "annotation": [
        {
          "type": "paragraph",
          "children": [
            {
              "text": "Yes! They wanted to get access to higher education, cause they were all channeled into vocational schools. Which is what Edgewood was doing, which is what my parents did not want for us. You know, and the one thing I remember my mother saying, “Te pueden quitar todo.” They can't take your education from you. Bloom. And you're gonna go to school. And you're gonna go to school."
            }
          ]
        }
      ],
      "tags": [
        {
          "tag": "Discrimination",
          "category": "Discrimination"
        },
        {
          "tag": "Edgewood High School",
          "category": "Schools and Education"
        },
        {
          "tag": "School Walkouts",
          "category": "Activism"
        },
        {
          "category": "Schools and Education",
          "tag": "Education"
        }
      ],
      "uuid": "f2226631-a8fa-4093-a4c0-b9af2e566ab1"
    },
    {
      "start_time": 211,
      "end_time": 267,
      "annotation": [
        {
          "type": "paragraph",
          "children": [
            {
              "text": "She worked as a seamstress at Fine Silver, they did piece work. And you know what piece work is? Where they do the little tickets, you know? And that’s how she got paid. She didn't have sick leave. She didn't have any insurance. She did not have any benefits, whatsoever. None. But she did that so she could pay for our tuition to go to Catholic school. And man, when I think about all she put up with. You know, years! I mean I'm talking about. And I rememever when she- She didn't work until David was, until David went to school, I don't think. But I remember when she use to leave us behind, and me and Johnny we used to go crying like ki- little babies. You know, “Don’t leave us! Don’t leave us!” And she would drop us off at one of the neighbor’s house. She used to take care of us. You know, and so, it was just somethin'."
            }
          ]
        }
      ],
      "tags": [
        {
          "tag": "Family Life",
          "category": "Personal Life"
        },
        {
          "category": "Race, Gender, and Class",
          "tag": "Class Dynamics"
        }
      ],
      "uuid": "0c849c0f-7ca2-43b4-aa68-b340dc06b325"
    },
    {
      "start_time": 267,
      "end_time": 273,
      "annotation": [
        {
          "type": "paragraph",
          "children": [
            {
              "text": "She must have been proud when David and you finished school?"
            }
          ]
        }
      ],
      "tags": [
        {
          "category": "Interviewer Question",
          "tag": "Question About Family Life"
        }
      ],
      "uuid": "8f93eb57-a985-41de-b3bd-6236b206cc9e"
    },
    {
      "start_time": 273,
      "end_time": 294,
      "annotation": [
        {
          "type": "paragraph",
          "children": [
            {
              "text": "Oh yeah yeah, she really was. That's the one thing, she made my graduations- all of them. The two graduations she went to, right when I got my masters she- she was there. My father wasn't because he had passed away, but I am sure he would have been there too. That was something."
            }
          ]
        }
      ],
      "tags": [
        {
          "tag": "Family Life",
          "category": "Personal Life"
        },
        {
          "category": "Race, Gender, and Class",
          "tag": "Class Dynamics"
        }
      ],
      "uuid": "02a51ec6-b8ce-40c4-9673-b46fc5db7225"
    },
    {
      "start_time": 294,
      "end_time": 302,
      "annotation": [
        {
          "type": "paragraph",
          "children": [
            {
              "text": "Tell me about the time you're serving as, you're working with Joe Bernal at Guadalupe Community Center?"
            }
          ]
        }
      ],
      "tags": [
        {
          "tag": "Question About Activism",
          "category": "Interviewer Question"
        }
      ],
      "uuid": "091ef9d0-e454-4c62-88f4-8fed59b9c98a"
    },
    {
      "start_time": 302,
      "end_time": 328,
      "annotation": [
        {
          "type": "paragraph",
          "children": [
            {
              "text": "I was an intern, he was with I'm trying to remember the exact name, but I think it was the Mexican American- The Commission for Mexican American Affairs- because from Guadalupe we moved to a house on Buena Vista Street. And Joe was very involved in the Raza Unida Movement, you know."
            }
          ]
        }
      ],
      "tags": [
        {
          "tag": "Joe Bernal",
          "category": "People"
        },
        {
          "tag": "La Raza Unida",
          "category": "Political Organizations"
        },
        {
          "category": "Political Organizations",
          "tag": "Mexican American Affairs Committee"
        }
      ],
      "uuid": "a52eae0e-cdea-470f-bb3c-e71a39def187"
    },
    {
      "start_time": 328,
      "end_time": 331,
      "annotation": [
        {
          "type": "paragraph",
          "children": [
            {
              "text": "What year are we talking about?"
            }
          ]
        }
      ],
      "tags": [
        {
          "tag": "Question About Activism",
          "category": "Interviewer Question"
        }
      ],
      "uuid": "f8973009-408b-42e8-9323-596c35f6aa4e"
    },
    {
      "start_time": 331,
      "end_time": 343,
      "annotation": [
        {
          "type": "paragraph",
          "children": [
            {
              "text": "Gosh. Well, I want to say ’68-’69 all the way through the 70s. Joe still remembers me too, you know."
            }
          ]
        }
      ],
      "tags": [
        {
          "tag": "Joe Bernal",
          "category": "People"
        },
        {
          "tag": "La Raza Unida",
          "category": "Political Organizations"
        }
      ],
      "uuid": "b7c7be96-db25-4476-b3c8-34f326d875b3"
    },
    {
      "start_time": 343,
      "end_time": 345,
      "annotation": [
        {
          "type": "paragraph",
          "children": [
            {
              "text": "So he was a state senator?"
            }
          ]
        }
      ],
      "tags": [
        {
          "tag": "Question About Activism",
          "category": "Interviewer Question"
        }
      ],
      "uuid": "92c50230-b7e2-46d5-9d52-30a0bd154c17"
    },
    {
      "start_time": 345,
      "end_time": 370,
      "annotation": [
        {
          "type": "paragraph",
          "children": [
            {
              "text": "He was former state senator, yeah. Co-author of the first- state’s first education- bilingual education bill. He is Dr. Bernal, now. He has been a doctor for a while now. \"We're gonna interview him.\" Oh good. Tell him you interviewed me. He's gonna tell you. Muchacha (laughter)."
            }
          ]
        }
      ],
      "tags": [
        {
          "tag": "Joe Bernal",
          "category": "People"
        }
      ],
      "uuid": "2f9d4d50-6b8b-47f4-9604-7ff2e5b91994"
    },
    {
      "start_time": 305,
      "end_time": 321,
      "annotation": [
        {
          "type": "paragraph",
          "children": [
            {
              "text": "The Mexican American Affairs Committee was a committee of the Texas AFL-CIO, an organization that opperated from 1951 to 1971 and represented labor interests at the state level. It's records are located at the University of Texas at Arlington."
            }
          ]
        }
      ],
      "tags": [
        {
          "category": "Political Organizations",
          "tag": "Mexican American Affairs Committee"
        },
        {
          "tag": "Political Context",
          "category": "Context"
        }
      ],
      "uuid": "048612b3-29f3-4c42-8cc0-dbfd1e9fdc3b"
    },
    {
      "start_time": 321,
      "end_time": 328,
      "annotation": [
        {
          "type": "paragraph",
          "children": [
            {
              "text": "La Raza Unida Party (RUP) was a political party formed in Crystal City, Texas in 1970. It's goals were to increase poltical respresentation for Mexican Americans as well as ecomic social conditions. It's state convention was held in San Antonio in 1971, and it's first national convention in El Paso in 1972. RUP was able to get many of its candidates elected in local positons in Kyle, Lockhart, Crystal City, and other cities in South Texas. It's records are located at the Benson Latin American Collection at the University of Texas at Austin."
            }
          ]
        }
      ],
      "tags": [
        {
          "tag": "La Raza Unida",
          "category": "Political Organizations"
        },
        {
          "tag": "Political Context",
          "category": "Context"
        }
      ],
      "uuid": "386f4491-941a-4c0e-b439-c6a9fa6fc9e6"
    },
    {
      "start_time": 42,
      "end_time": 95,
      "annotation": [
        {
          "type": "paragraph",
          "children": [
            {
              "text": "The Nation of Islam (NOI) is a movement which differs substantially from traditional Sunni or Shia interpretations of the religion found in majority Muslim Countries. It was founded in 1930 by Wallace Fard Muhammad in the city of Detriot, Michigan. It promotes Black Nationalism, an ideology that advocates for self-determination and a national identity for black people, particularly in the United States. One of the most famous members of the NOI is Malcom X, who joined the movement while imprisioned between 1948 and 1952. He left it in 1964 following an ideological split."
            }
          ]
        }
      ],
      "tags": [
        {
          "category": "Context",
          "tag": "Politcal Context"
        },
        {
          "tag": "The Nation of Islam",
          "category": "Political Organizations"
        }
      ],
      "uuid": "668fb084-d364-4601-b5b9-66689b4a29c0"
    }
  ],
  "set": "Default",
  "event_id": "c33598e1-a70b-4df0-9c20-2409646acf19",
  "source_id": "bd4cd099-3f19-4fe1-9173-c504d2161b46"
}